pyf_collection/__init__.py
pyf_collection/core.py
pyf_collection-0.1.4.dist-info/licenses/LICENSE
pyf_collection-0.1.4.dist-info/METADATA
pyf_collection-0.1.4.dist-info/WHEEL
pyf_collection-0.1.4.dist-info/top_level.txt
pyf_collection-0.1.4.dist-info/RECORD
