Metadata-Version: 2.4
Name: pyf-collection
Version: 0.1.4
Author: Pablo Picouto Garcia
License: Copyright (c) 2025 Pablo
Project-URL: Homepage, https://github.com/politrons/Dive-into-Python
Project-URL: Issues, https://github.com/politrons/Dive-into-Python
Keywords: collection,monads,list,map,functional
Classifier: Programming Language :: Python :: 3
Classifier: License :: OSI Approved :: MIT License
Classifier: Typing :: Typed
Requires-Python: >=3.9
License-File: LICENSE
Dynamic: license-file
